{
  "citations": [
    {
      "citation_id": "cit-001",
      "locator": "email body",
      "quote": "Accommodation Arrears as of 10th April \u00a35,526.66",
      "target_id": "NAP-SRC-0048",
      "target_type": "source"
    },
    {
      "citation_id": "cit-002",
      "locator": "email body",
      "quote": "If payment is not made by this date, then the notice to quit will be enforced as per your tenancy agreement.",
      "target_id": "NAP-SRC-0048",
      "target_type": "source"
    },
    {
      "citation_id": "cit-003",
      "locator": "email body",
      "quote": "you provided a signed Guarantee Form which explained that if you did not pay your rent, your guarantor would be given full details of your rent arrears",
      "target_id": "NAP-SRC-0048",
      "target_type": "source"
    },
    {
      "citation_id": "cit-004",
      "locator": "Award Notice",
      "quote": "Paramedic, Nursing and Midwifery Bursary \u00a310,000.00",
      "target_id": "NAP-SRC-0001",
      "target_type": "source"
    },
    {
      "citation_id": "cit-005",
      "locator": "email body",
      "quote": "I would like to confirm my receipt of a Notice to Quit letter",
      "target_id": "NAP-SRC-0048",
      "target_type": "source"
    },
    {
      "citation_id": "cit-006",
      "locator": "email body",
      "quote": "setting a requirement to pay by 9 May 2026",
      "target_id": "NAP-SRC-0048",
      "target_type": "source"
    }
  ],
  "contradictions": [],
  "external_action_requests": [],
  "findings": [
    {
      "citation_ids": [
        "cit-001"
      ],
      "confidence": 0.9,
      "finding_id": "f-001",
      "finding_type": "fact",
      "reasoning_status": "supported",
      "text": "Anfal Elbushra owes \u00a35,526.66 in accommodation arrears as of 10 April 2026."
    },
    {
      "citation_ids": [
        "cit-004"
      ],
      "confidence": 0.9,
      "finding_id": "f-002",
      "finding_type": "fact",
      "reasoning_status": "supported",
      "text": "SAAS awarded Anfal Elbushra a \u00a310,000 Nursing and Midwifery Bursary for 2025-2026."
    },
    {
      "citation_ids": [
        "cit-005",
        "cit-006"
      ],
      "confidence": 0.9,
      "finding_id": "f-003",
      "finding_type": "fact",
      "reasoning_status": "supported",
      "text": "A Notice to Quit has been issued with a payment deadline of 9 May 2026."
    },
    {
      "citation_ids": [
        "cit-003"
      ],
      "confidence": 0.9,
      "finding_id": "f-004",
      "finding_type": "fact",
      "reasoning_status": "supported",
      "text": "A signed Guarantee Form exists, making a guarantor liable for missed rent."
    }
  ],
  "proposed_artifacts": [
    {
      "artifact_type": "evidence_gap_report",
      "content": "## Missing Documents Identified\n\nBased on review of NAP-SRC-0001, NAP-SRC-0038, and NAP-SRC-0048, the following documents are referenced but not present in the current evidence bundle:\n\n1. **Tenancy Agreement** \u2013 Referenced in NAP-SRC-0048 as the basis for the Notice to Quit enforcement.\n2. **Notice to Quit Letter** \u2013 Confirmed received by Anfal Elbushra (NAP-SRC-0048), but the letter itself is missing.\n3. **Guarantee Form** \u2013 Signed by the student, making a guarantor liable for arrears (NAP-SRC-0048).\n4. **Payment Plan Correspondence** \u2013 Anfal requested a payment plan; no response from the university is in the bundle.\n5. **University Support Services Communications** \u2013 Anfal mentioned contact with support services; no related emails are present.\n\n**Recommendation**: Retrieve these documents to verify the legal basis for the arrears and the Notice to Quit.",
      "path": "candidate/bundle-01-followup/missing-documents-list.md",
      "stage": "S2",
      "title": "Missing Documents Referenced in Bundle 01"
    }
  ],
  "proposed_tasks": [
    {
      "artifact_dependencies": [
        "candidate/bundle-01-followup/missing-documents-list.md"
      ],
      "instructions": "Search the matter source inventory and any linked email archives for the following documents referenced in NAP-SRC-0048: (1) the signed tenancy agreement for Castlelaw House, (2) the Notice to Quit letter issued to Anfal Elbushra, (3) the signed Guarantee Form, and (4) any correspondence regarding a payment plan or university support services. If found, add them to the evidence bundle and re-run the evidence gap analysis.",
      "matter_scope": "napier-accommodation-arrears",
      "source_dependencies": [
        "NAP-SRC-0001",
        "NAP-SRC-0048",
        "NAP-SRC-0038"
      ],
      "stage": "S2",
      "task_id": "bundle-01-followup-retrieve",
      "task_type": "evidence_gap_fill",
      "title": "Retrieve missing tenancy agreement, Notice to Quit, Guarantee Form, and payment plan correspondence",
      "validation_gates": [
        "claim_evidence_support",
        "stale_dependency"
      ]
    }
  ],
  "redaction_flags": [
    {
      "citation_ids": [
        "cit-001"
      ],
      "confidence": 0.9,
      "finding_id": "red-001",
      "finding_type": "redaction_flag",
      "reasoning_status": "supported",
      "text": "NAP-SRC-0048 contains the student's full name, address, and student number; consider redacting before external sharing."
    },
    {
      "citation_ids": [
        "cit-004"
      ],
      "confidence": 0.9,
      "finding_id": "red-002",
      "finding_type": "redaction_flag",
      "reasoning_status": "supported",
      "text": "NAP-SRC-0001 contains the student's full name, address, and partial bank account number; consider redacting."
    }
  ],
  "risk_flags": [
    {
      "citation_ids": [
        "cit-002"
      ],
      "confidence": 0.9,
      "finding_id": "r-001",
      "finding_type": "risk",
      "reasoning_status": "supported",
      "text": "Enforcement of the Notice to Quit is imminent if the 9 May 2026 deadline is not met."
    },
    {
      "citation_ids": [
        "cit-003"
      ],
      "confidence": 0.9,
      "finding_id": "r-002",
      "finding_type": "risk",
      "reasoning_status": "supported",
      "text": "The guarantor may become liable for the full arrears, creating potential secondary liability."
    },
    {
      "citation_ids": [],
      "confidence": 0.0,
      "finding_id": "r-003",
      "finding_type": "risk",
      "reasoning_status": "uncertain",
      "text": "Without the tenancy agreement, the legal basis for the arrears and notice to quit cannot be fully verified."
    }
  ],
  "schema_version": "worker_result_packet.v2",
  "summary": "Reviewed three sources for bundle-01 followup. NAP-SRC-0048 shows Anfal Elbushra owes \u00a35,526.66 in accommodation arrears as of 10 April 2026, with a Notice to Quit issued and a 9 May 2026 deadline. NAP-SRC-0001 confirms SAAS bursary payments of \u00a310,000 for 2025-2026. NAP-SRC-0038 is a fire safety policy email. Key missing documents: the tenancy agreement, the Notice to Quit, the Guarantee Form, and any payment plan correspondence. Proposed follow-up task to retrieve these.",
  "task_id": "bundle-01-followup",
  "uncertainties": [
    {
      "citation_ids": [],
      "confidence": 0.0,
      "finding_id": "u-001",
      "finding_type": "uncertainty",
      "reasoning_status": "uncertain",
      "text": "The tenancy agreement terms, including the Notice to Quit enforcement process, are not provided in the current sources."
    },
    {
      "citation_ids": [],
      "confidence": 0.0,
      "finding_id": "u-002",
      "finding_type": "uncertainty",
      "reasoning_status": "uncertain",
      "text": "The Guarantee Form and the identity/contact of the guarantor are not in the evidence bundle."
    },
    {
      "citation_ids": [],
      "confidence": 0.0,
      "finding_id": "u-003",
      "finding_type": "uncertainty",
      "reasoning_status": "uncertain",
      "text": "No payment plan or correspondence from university support services is present in the provided sources."
    }
  ]
}